wgtool/__init__.py
wgtool/cli.py
wgtool/exceptions.py
wgtool/exporter.py
wgtool/host.py
wgtool/importer.py
wgtool/models.py
wgtool/post.py
wgtool/qrcode.py
wgtool/wgcli.py
wgtool/wgtool.py
wgtool-1.1.14.dist-info/LICENSE
wgtool-1.1.14.dist-info/METADATA
wgtool-1.1.14.dist-info/WHEEL
wgtool-1.1.14.dist-info/entry_points.txt
wgtool-1.1.14.dist-info/top_level.txt
wgtool-1.1.14.dist-info/RECORD
