Metadata-Version: 2.1
Name: wgtool
Version: 1.1.14
Summary: WireGuard Configuration Tool
Home-page: https://github.com/rpcsp/wgtool
Author: rpcsp
Author-email: pcunha@hotmail.com
License: https://github.com/rpcsp/wgtool/blob/main/LICENSE
Project-URL: Project page, https://github.com/rpcsp/wgtool
Classifier: Operating System :: OS Independent
Classifier: Programming Language :: Python :: 3
Classifier: Programming Language :: Python :: 3.7
Classifier: Programming Language :: Python :: 3.8
Classifier: Programming Language :: Python :: 3.9
Classifier: Programming Language :: Python :: 3.10
Requires-Python: >=3.7
License-File: LICENSE
Requires-Dist: pydantic
Requires-Dist: qrcode
